lidarwind/__init__.py
lidarwind/data_attributes.py
lidarwind/data_operator.py
lidarwind/filters.py
lidarwind/io.py
lidarwind/lidar_code.py
lidarwind/lidarwind_config.py
lidarwind/utilities.py
lidarwind/version.py
lidarwind/visualization.py
lidarwind/wind_prop_retrieval.py
lidarwind/wind_prop_retrieval_6_beam.py
lidarwind/postprocessing/__init__.py
lidarwind/postprocessing/post_rpg_radar.py
lidarwind/postprocessing/post_wind_cube.py
lidarwind/preprocessing/__init__.py
lidarwind/preprocessing/rpg_radar.py
lidarwind/preprocessing/wind_cube.py
lidarwind/wind_retrieval/__init__.py
lidarwind/wind_retrieval/fft_wind_retrieval.py
lidarwind-1.0.1.dist-info/AUTHORS.rst
lidarwind-1.0.1.dist-info/LICENSE
lidarwind-1.0.1.dist-info/METADATA
lidarwind-1.0.1.dist-info/WHEEL
lidarwind-1.0.1.dist-info/entry_points.txt
lidarwind-1.0.1.dist-info/top_level.txt
lidarwind-1.0.1.dist-info/RECORD
