Metadata-Version: 2.1
Name: lidarwind
Version: 1.0.1
Summary: LIDAR procedures
Author: José Dias Neto
Author-email: jdiasn@gmail.com
License: 
Project-URL: homepage, https://github.com/jdiasn/lidarwind
Project-URL: repository, https://github.com/jdiasn/lidarwind
Project-URL: documentation, https://lidarwind.readthedocs.io
Keywords: Lidar,Turbulence,Wind
Classifier: Development Status :: 2 - Pre-Alpha
Classifier: Intended Audience :: Science/Research
Classifier: License :: OSI Approved :: BSD License
Classifier: Natural Language :: English
Classifier: Programming Language :: Python :: 3
Classifier: Programming Language :: Python :: 3.8
Classifier: Programming Language :: Python :: 3.9
Classifier: Programming Language :: Python :: 3.10
Classifier: Topic :: Scientific/Engineering
Requires-Python: >=3.8
License-File: LICENSE
License-File: AUTHORS.rst
Requires-Dist: xrft>=0.3
Requires-Dist: xarray>=0.21
Requires-Dist: pandas>=1.4
Requires-Dist: numpy>=1.22
Requires-Dist: netCDF4>=1.5
Requires-Dist: matplotlib>=3.4.3
Requires-Dist: click>=8.1.2
Requires-Dist: gdown>=4.5.1
Requires-Dist: xarray-datatree~=0.0.11
Requires-Dist: pooch>=1.6
Provides-Extra: dev
Requires-Dist: flake8~=4.0.1; extra == "dev"
Requires-Dist: pre-commit~=2.20.0; extra == "dev"
Requires-Dist: ruff~=0.0.220; extra == "dev"
Requires-Dist: sphinx-rtd-theme~=0.4.3; extra == "dev"
Provides-Extra: plots
Requires-Dist: matplotlib>=3.4.3; extra == "plots"
Provides-Extra: test
Requires-Dist: gdown>=4.5.1; extra == "test"
Requires-Dist: pytest>=6.2; extra == "test"
Requires-Dist: pytest-cov>=3.0; extra == "test"
Requires-Dist: nbval; extra == "test"
Requires-Dist: pooch>=1.6; extra == "test"
Requires-Dist: tox~=4.3.0; extra == "test"
